prayer/__init__.py
prayer/blocks.py
prayer/prayer.py
prayer-0.1.1.dist-info/LICENSE
prayer-0.1.1.dist-info/METADATA
prayer-0.1.1.dist-info/WHEEL
prayer-0.1.1.dist-info/top_level.txt
prayer-0.1.1.dist-info/RECORD
