Metadata-Version: 2.1
Name: prayer
Version: 0.1.1
Summary: Library, for working with PRAY files.
Home-page: https://github.com/Creatures-Developer-Network/prayer
Author: KeyboardInterrupt
Author-email: keyboardinterrupt@keyboardinterrupt.com
License: UNKNOWN
Platform: UNKNOWN
Classifier: Programming Language :: Python :: 3
Classifier: License :: OSI Approved :: MIT License
Classifier: Operating System :: OS Independent
Requires-Python: >=3.6
